{
  "appleCabin": [
    {
      "id": "1",
      "original": "/images/apple-cabin/1.png",
      "webp": "/images/apple-cabin/webp/1.webp"
    },
    {
      "id": "2",
      "original": "/images/apple-cabin/2.png",
      "webp": "/images/apple-cabin/webp/2.webp"
    },
    {
      "id": "3",
      "original": "/images/apple-cabin/3.jpg",
      "webp": "/images/apple-cabin/webp/3.webp"
    },
    {
      "id": "4",
      "original": "/images/apple-cabin/4.png",
      "webp": "/images/apple-cabin/webp/4.webp"
    },
    {
      "id": "5",
      "original": "/images/apple-cabin/5.png",
      "webp": "/images/apple-cabin/webp/5.webp"
    },
    {
      "id": "6",
      "original": "/images/apple-cabin/6.png",
      "webp": "/images/apple-cabin/webp/6.webp"
    },
    {
      "id": "7",
      "original": "/images/apple-cabin/7.png",
      "webp": "/images/apple-cabin/webp/7.webp"
    },
    {
      "id": "8",
      "original": "/images/apple-cabin/8.png",
      "webp": "/images/apple-cabin/webp/8.webp"
    },
    {
      "id": "9",
      "original": "/images/apple-cabin/9.jpg",
      "webp": "/images/apple-cabin/webp/9.webp"
    },
    {
      "id": "10",
      "original": "/images/apple-cabin/10.png",
      "webp": "/images/apple-cabin/webp/10.webp"
    },
    {
      "id": "11",
      "original": "/images/apple-cabin/11.jpg",
      "webp": "/images/apple-cabin/webp/11.webp"
    },
    {
      "id": "12",
      "original": "/images/apple-cabin/12.png",
      "webp": "/images/apple-cabin/webp/12.webp"
    },
    {
      "id": "13",
      "original": "/images/apple-cabin/13.jpg",
      "webp": "/images/apple-cabin/webp/13.webp"
    },
    {
      "id": "14",
      "original": "/images/apple-cabin/14.jpg",
      "webp": "/images/apple-cabin/webp/14.webp"
    },
    {
      "id": "15",
      "original": "/images/apple-cabin/15.png",
      "webp": "/images/apple-cabin/webp/15.webp"
    },
    {
      "id": "16",
      "original": "/images/apple-cabin/16.jpg",
      "webp": "/images/apple-cabin/webp/16.webp"
    },
    {
      "id": "17",
      "original": "/images/apple-cabin/17.jpg",
      "webp": "/images/apple-cabin/webp/17.webp"
    },
    {
      "id": "18",
      "original": "/images/apple-cabin/18.png",
      "webp": "/images/apple-cabin/webp/18.webp"
    },
    {
      "id": "19",
      "original": "/images/apple-cabin/19.png",
      "webp": "/images/apple-cabin/webp/19.webp"
    },
    {
      "id": "20",
      "original": "/images/apple-cabin/20.jpg",
      "webp": "/images/apple-cabin/webp/20.webp"
    },
    {
      "id": "21",
      "original": "/images/apple-cabin/21.jpg",
      "webp": "/images/apple-cabin/webp/21.webp"
    },
    {
      "id": "22",
      "original": "/images/apple-cabin/22.jpg",
      "webp": "/images/apple-cabin/webp/22.webp"
    },
    {
      "id": "23",
      "original": "/images/apple-cabin/23.jpg",
      "webp": "/images/apple-cabin/webp/23.webp"
    },
    {
      "id": "24",
      "original": "/images/apple-cabin/24.jpg",
      "webp": "/images/apple-cabin/webp/24.webp"
    },
    {
      "id": "25",
      "original": "/images/apple-cabin/25.png",
      "webp": "/images/apple-cabin/webp/25.webp"
    },
    {
      "id": "26",
      "original": "/images/apple-cabin/26.png",
      "webp": "/images/apple-cabin/webp/26.webp"
    },
    {
      "id": "27",
      "original": "/images/apple-cabin/27.png",
      "webp": "/images/apple-cabin/webp/27.webp"
    },
    {
      "id": "28",
      "original": "/images/apple-cabin/28.png",
      "webp": "/images/apple-cabin/webp/28.webp"
    },
    {
      "id": "29",
      "original": "/images/apple-cabin/29.png",
      "webp": "/images/apple-cabin/webp/29.webp"
    },
    {
      "id": "30",
      "original": "/images/apple-cabin/30.png",
      "webp": "/images/apple-cabin/webp/30.webp"
    },
    {
      "id": "31",
      "original": "/images/apple-cabin/31.png",
      "webp": "/images/apple-cabin/webp/31.webp"
    },
    {
      "id": "32",
      "original": "/images/apple-cabin/32.png",
      "webp": "/images/apple-cabin/webp/32.webp"
    },
    {
      "id": "33",
      "original": "/images/apple-cabin/33.png",
      "webp": "/images/apple-cabin/webp/33.webp"
    },
    {
      "id": "34",
      "original": "/images/apple-cabin/34.png",
      "webp": "/images/apple-cabin/webp/34.webp"
    },
    {
      "id": "35",
      "original": "/images/apple-cabin/35.png",
      "webp": "/images/apple-cabin/webp/35.webp"
    },
    {
      "id": "36",
      "original": "/images/apple-cabin/36.png",
      "webp": "/images/apple-cabin/webp/36.webp"
    },
    {
      "id": "37",
      "original": "/images/apple-cabin/37.png",
      "webp": "/images/apple-cabin/webp/37.webp"
    },
    {
      "id": "38",
      "original": "/images/apple-cabin/38.png",
      "webp": "/images/apple-cabin/webp/38.webp"
    },
    {
      "id": "39",
      "original": "/images/apple-cabin/39.png",
      "webp": "/images/apple-cabin/webp/39.webp"
    },
    {
      "id": "40",
      "original": "/images/apple-cabin/40.png",
      "webp": "/images/apple-cabin/webp/40.webp"
    },
    {
      "id": "41",
      "original": "/images/apple-cabin/41.jpg",
      "webp": "/images/apple-cabin/webp/41.webp"
    },
    {
      "id": "42",
      "original": "/images/apple-cabin/42.png",
      "webp": "/images/apple-cabin/webp/42.webp"
    },
    {
      "id": "43",
      "original": "/images/apple-cabin/43.png",
      "webp": "/images/apple-cabin/webp/43.webp"
    },
    {
      "id": "44",
      "original": "/images/apple-cabin/44.jpg",
      "webp": "/images/apple-cabin/webp/44.webp"
    },
    {
      "id": "45",
      "original": "/images/apple-cabin/45.jpg",
      "webp": "/images/apple-cabin/webp/45.webp"
    },
    {
      "id": "46",
      "original": "/images/apple-cabin/46.jpg",
      "webp": "/images/apple-cabin/webp/46.webp"
    },
    {
      "id": "47",
      "original": "/images/apple-cabin/47.png",
      "webp": "/images/apple-cabin/webp/47.webp"
    },
    {
      "id": "48",
      "original": "/images/apple-cabin/48.png",
      "webp": "/images/apple-cabin/webp/48.webp"
    },
    {
      "id": "49",
      "original": "/images/apple-cabin/49.jpg",
      "webp": "/images/apple-cabin/webp/49.webp"
    },
    {
      "id": "50",
      "original": "/images/apple-cabin/50.jpg",
      "webp": "/images/apple-cabin/webp/50.webp"
    },
    {
      "id": "51",
      "original": "/images/apple-cabin/51.png",
      "webp": "/images/apple-cabin/webp/51.webp"
    },
    {
      "id": "52",
      "original": "/images/apple-cabin/52.png",
      "webp": "/images/apple-cabin/webp/52.webp"
    },
    {
      "id": "53",
      "original": "/images/apple-cabin/53.png",
      "webp": "/images/apple-cabin/webp/53.webp"
    }
  ],
  "expandable": [
    {
      "id": "1",
      "original": "/images/expandable/1.png",
      "webp": "/images/expandable/webp/1.webp"
    },
    {
      "id": "2",
      "original": "/images/expandable/2.png",
      "webp": "/images/expandable/webp/2.webp"
    },
    {
      "id": "3",
      "original": "/images/expandable/3.png",
      "webp": "/images/expandable/webp/3.webp"
    },
    {
      "id": "4",
      "original": "/images/expandable/4.jpg",
      "webp": "/images/expandable/webp/4.webp"
    },
    {
      "id": "5",
      "original": "/images/expandable/5.jpg",
      "webp": "/images/expandable/webp/5.webp"
    },
    {
      "id": "6",
      "original": "/images/expandable/6.jpg",
      "webp": "/images/expandable/webp/6.webp"
    },
    {
      "id": "7",
      "original": "/images/expandable/7.png",
      "webp": "/images/expandable/webp/7.webp"
    },
    {
      "id": "8",
      "original": "/images/expandable/8.png",
      "webp": "/images/expandable/webp/8.webp"
    },
    {
      "id": "9",
      "original": "/images/expandable/9.png",
      "webp": "/images/expandable/webp/9.webp"
    },
    {
      "id": "10",
      "original": "/images/expandable/10.png",
      "webp": "/images/expandable/webp/10.webp"
    },
    {
      "id": "11",
      "original": "/images/expandable/11.jpg",
      "webp": "/images/expandable/webp/11.webp"
    },
    {
      "id": "12",
      "original": "/images/expandable/12.jpg",
      "webp": "/images/expandable/webp/12.webp"
    },
    {
      "id": "13",
      "original": "/images/expandable/13.jpg",
      "webp": "/images/expandable/webp/13.webp"
    },
    {
      "id": "14",
      "original": "/images/expandable/14.jpg",
      "webp": "/images/expandable/webp/14.webp"
    },
    {
      "id": "15",
      "original": "/images/expandable/15.jpg",
      "webp": "/images/expandable/webp/15.webp"
    },
    {
      "id": "16",
      "original": "/images/expandable/16.png",
      "webp": "/images/expandable/webp/16.webp"
    },
    {
      "id": "17",
      "original": "/images/expandable/17.png",
      "webp": "/images/expandable/webp/17.webp"
    },
    {
      "id": "18",
      "original": "/images/expandable/18.png",
      "webp": "/images/expandable/webp/18.webp"
    },
    {
      "id": "19",
      "original": "/images/expandable/19.jpg",
      "webp": "/images/expandable/webp/19.webp"
    },
    {
      "id": "20",
      "original": "/images/expandable/20.png",
      "webp": "/images/expandable/webp/20.webp"
    },
    {
      "id": "21",
      "original": "/images/expandable/21.jpg",
      "webp": "/images/expandable/webp/21.webp"
    },
    {
      "id": "22",
      "original": "/images/expandable/22.png",
      "webp": "/images/expandable/webp/22.webp"
    },
    {
      "id": "23",
      "original": "/images/expandable/23.png",
      "webp": "/images/expandable/webp/23.webp"
    },
    {
      "id": "24",
      "original": "/images/expandable/24.jpg",
      "webp": "/images/expandable/webp/24.webp"
    },
    {
      "id": "25",
      "original": "/images/expandable/25.jpg",
      "webp": "/images/expandable/webp/25.webp"
    },
    {
      "id": "26",
      "original": "/images/expandable/26.png",
      "webp": "/images/expandable/webp/26.webp"
    },
    {
      "id": "27",
      "original": "/images/expandable/27.png",
      "webp": "/images/expandable/webp/27.webp"
    },
    {
      "id": "28",
      "original": "/images/expandable/28.png",
      "webp": "/images/expandable/webp/28.webp"
    },
    {
      "id": "29",
      "original": "/images/expandable/29.png",
      "webp": "/images/expandable/webp/29.webp"
    },
    {
      "id": "30",
      "original": "/images/expandable/30.png",
      "webp": "/images/expandable/webp/30.webp"
    },
    {
      "id": "31",
      "original": "/images/expandable/31.png",
      "webp": "/images/expandable/webp/31.webp"
    },
    {
      "id": "32",
      "original": "/images/expandable/32.png",
      "webp": "/images/expandable/webp/32.webp"
    },
    {
      "id": "33",
      "original": "/images/expandable/33.jpg",
      "webp": "/images/expandable/webp/33.webp"
    },
    {
      "id": "34",
      "original": "/images/expandable/34.jpg",
      "webp": "/images/expandable/webp/34.webp"
    },
    {
      "id": "35",
      "original": "/images/expandable/35.png",
      "webp": "/images/expandable/webp/35.webp"
    },
    {
      "id": "36",
      "original": "/images/expandable/36.jpg",
      "webp": "/images/expandable/webp/36.webp"
    },
    {
      "id": "37",
      "original": "/images/expandable/37.jpg",
      "webp": "/images/expandable/webp/37.webp"
    },
    {
      "id": "38",
      "original": "/images/expandable/38.jpg",
      "webp": "/images/expandable/webp/38.webp"
    },
    {
      "id": "39",
      "original": "/images/expandable/39.jpg",
      "webp": "/images/expandable/webp/39.webp"
    },
    {
      "id": "40",
      "original": "/images/expandable/40.png",
      "webp": "/images/expandable/webp/40.webp"
    }
  ]
}